Handlers/__init__.py
Handlers/byte.py
Handlers/files_handler.py
KLog/KLog.py
KLog/__init__.py
KLogLib-0.2.0.dist-info/LICENSE
KLogLib-0.2.0.dist-info/METADATA
KLogLib-0.2.0.dist-info/WHEEL
KLogLib-0.2.0.dist-info/top_level.txt
KLogLib-0.2.0.dist-info/RECORD
