Metadata-Version: 2.1
Name: KLogLib
Version: 0.2.0
Home-page: https://github.com/javifriasj/KLog/releases/tag/0.2.0
License-File: LICENSE
